{
  "width": 13,
  "height": 6.75,
  "name": "Launchkey Mini MK3 DAW Port",
  "type": "normal",
  "style": {
    "borderTopLeftRadius": "0.5em",
    "borderTopRightRadius": "0.5em",
    "borderBottomLeftRadius": "0.5em",
    "borderBottomRightRadius": "0.5em"
  },
  "keyboard": {
    "defaultOctave": 2,
    "nOctaves": 2,
    "channel": 0,
    "width": 11.625,
    "height": 3.125,
    "left": 0.625,
    "bottom": 0,
    "enabled": false
  },
  "controlSequence": [
    [
      "noteoff",
      96,
      0,
      0
    ],
    [
      "noteoff",
      97,
      0,
      0
    ],
    [
      "noteoff",
      98,
      0,
      0
    ],
    [
      "noteoff",
      99,
      0,
      0
    ],
    [
      "noteoff",
      100,
      0,
      0
    ],
    [
      "noteoff",
      101,
      0,
      0
    ],
    [
      "noteoff",
      102,
      0,
      0
    ],
    [
      "noteoff",
      103,
      0,
      0
    ],
    [
      "noteoff",
      112,
      0,
      0
    ],
    [
      "noteoff",
      113,
      0,
      0
    ],
    [
      "noteoff",
      114,
      0,
      0
    ],
    [
      "noteoff",
      115,
      0,
      0
    ],
    [
      "noteoff",
      116,
      0,
      0
    ],
    [
      "noteoff",
      117,
      0,
      0
    ],
    [
      "noteoff",
      118,
      0,
      0
    ],
    [
      "noteoff",
      119,
      0,
      0
    ],
    [
      "controlchange",
      104,
      0,
      0
    ],
    [
      "controlchange",
      103,
      0,
      15
    ],
    [
      "controlchange",
      102,
      63,
      15
    ],
    [
      "controlchange",
      115,
      0,
      15
    ],
    [
      "controlchange",
      117,
      0,
      15
    ],
    [
      "controlchange",
      105,
      1,
      0
    ],
    [
      "controlchange",
      21,
      108,
      15
    ],
    [
      "controlchange",
      22,
      108,
      15
    ],
    [
      "controlchange",
      23,
      108,
      15
    ],
    [
      "controlchange",
      24,
      108,
      15
    ],
    [
      "controlchange",
      21,
      108,
      15
    ],
    [
      "controlchange",
      22,
      108,
      15
    ],
    [
      "controlchange",
      23,
      108,
      15
    ],
    [
      "controlchange",
      24,
      108,
      15
    ],
    [
      "controlchange",
      3,
      1,
      15
    ],
    [
      "controlchange",
      105,
      0,
      0
    ],
    [
      "controlchange",
      102,
      0,
      15
    ],
    [
      "controlchange",
      108,
      0,
      0
    ],
    [
      "noteoff",
      48,
      0,
      9
    ],
    [
      "noteoff",
      49,
      0,
      9
    ],
    [
      "noteoff",
      50,
      0,
      9
    ],
    [
      "noteoff",
      51,
      0,
      9
    ],
    [
      "noteoff",
      44,
      0,
      9
    ],
    [
      "noteoff",
      45,
      0,
      9
    ],
    [
      "noteoff",
      46,
      0,
      9
    ],
    [
      "noteoff",
      47,
      0,
      9
    ],
    [
      "noteoff",
      40,
      0,
      9
    ],
    [
      "noteoff",
      41,
      0,
      9
    ],
    [
      "noteoff",
      42,
      0,
      9
    ],
    [
      "noteoff",
      43,
      0,
      9
    ],
    [
      "noteoff",
      36,
      0,
      9
    ],
    [
      "noteoff",
      37,
      0,
      9
    ],
    [
      "noteoff",
      38,
      0,
      9
    ],
    [
      "noteoff",
      39,
      0,
      9
    ],
    [
      "noteoff",
      12,
      0,
      15
    ],
    [
      "controlchange",
      3,
      0,
      15
    ],
    [
      "controlchange",
      9,
      0,
      15
    ],
    [
      "noteoff",
      96,
      0,
      0
    ],
    [
      "noteoff",
      97,
      0,
      0
    ],
    [
      "noteoff",
      98,
      0,
      0
    ],
    [
      "noteoff",
      99,
      0,
      0
    ],
    [
      "noteoff",
      100,
      0,
      0
    ],
    [
      "noteoff",
      101,
      0,
      0
    ],
    [
      "noteoff",
      102,
      0,
      0
    ],
    [
      "noteoff",
      103,
      0,
      0
    ],
    [
      "noteoff",
      112,
      0,
      0
    ],
    [
      "noteoff",
      113,
      0,
      0
    ],
    [
      "noteoff",
      114,
      0,
      0
    ],
    [
      "noteoff",
      115,
      0,
      0
    ],
    [
      "noteoff",
      116,
      0,
      0
    ],
    [
      "noteoff",
      117,
      0,
      0
    ],
    [
      "noteoff",
      118,
      0,
      0
    ],
    [
      "noteoff",
      119,
      0,
      0
    ],
    [
      "controlchange",
      104,
      0,
      0
    ],
    [
      "controlchange",
      103,
      0,
      15
    ],
    [
      "controlchange",
      102,
      63,
      15
    ],
    [
      "controlchange",
      115,
      0,
      15
    ],
    [
      "controlchange",
      117,
      0,
      15
    ],
    [
      "controlchange",
      21,
      108,
      15
    ],
    [
      "controlchange",
      22,
      108,
      15
    ],
    [
      "controlchange",
      23,
      108,
      15
    ],
    [
      "controlchange",
      24,
      108,
      15
    ],
    [
      "controlchange",
      21,
      108,
      15
    ],
    [
      "controlchange",
      22,
      108,
      15
    ],
    [
      "controlchange",
      23,
      108,
      15
    ],
    [
      "controlchange",
      24,
      108,
      15
    ],
    [
      "noteon",
      12,
      127,
      15
    ],
    [
      "controlchange",
      3,
      2,
      15
    ],
    [
      "controlchange",
      9,
      1,
      15
    ],
    [
      "controlchange",
      104,
      0,
      0
    ]
  ],
  "inputGrids": [
    {
      "id": "Wheels",
      "nRows": 1,
      "nCols": 2,
      "width": 1.25,
      "height": 2.25,
      "left": 0.6,
      "bottom": 3.875,
      "inputs": [
        {
          "handleWidth": 0.5,
          "handleHeight": 0.25,
          "number": 0
        },
        {
          "handleWidth": 0.5,
          "handleHeight": 0.25,
          "number": 1,
          "eventType": "controlchange"
        }
      ],
      "inputDefaults": {
        "availableColors": [],
        "type": "wheel",
        "width": 0.5,
        "height": 2.25,
        "shape": "rect",
        "overrideable": false,
        "response": "continuous",
        "eventType": "pitchbend",
        "channel": 0
      }
    },
    {
      "id": "Octaves",
      "nRows": 2,
      "nCols": 1,
      "width": 0.5,
      "height": 0.75,
      "left": 2.25,
      "bottom": 3.75,
      "inputs": [
        {
          "number": 0
        },
        {
          "number": -1,
          "eventType": "octdown"
        }
      ],
      "inputDefaults": {
        "availableColors": [],
        "type": "pad",
        "width": 0.5,
        "height": 0.25,
        "shape": "rect",
        "overrideable": false,
        "response": "constant",
        "eventType": "octup",
        "channel": 0
      }
    },
    {
      "id": "Transpose",
      "nRows": 1,
      "nCols": 1,
      "width": 0.5,
      "height": 0.25,
      "left": 2.25,
      "bottom": 5.125,
      "inputs": [
        {
          "number": 0
        }
      ],
      "inputDefaults": {
        "availableColors": [],
        "type": "pad",
        "width": 0.5,
        "height": 0.25,
        "shape": "rect",
        "overrideable": false,
        "response": "gate",
        "eventType": "octup",
        "channel": 0
      }
    },
    {
      "id": "Shift",
      "nRows": 1,
      "nCols": 1,
      "width": 0.5,
      "height": 0.25,
      "left": 2.25,
      "bottom": 5.875,
      "inputs": [
        {
          "number": 0
        }
      ],
      "inputDefaults": {
        "availableColors": [],
        "type": "pad",
        "width": 0.5,
        "height": 0.25,
        "shape": "rect",
        "overrideable": false,
        "response": "gate",
        "eventType": "octup",
        "channel": 0
      }
    },
    {
      "id": "Pads",
      "nRows": 2,
      "nCols": 9,
      "width": 7.625,
      "height": 1.6,
      "left": 3.125,
      "bottom": 3.75,
      "inputs": [
        {
          "number": 96
        },
        {
          "number": 97
        },
        {
          "number": 98
        },
        {
          "number": 99
        },
        {
          "number": 100
        },
        {
          "number": 101
        },
        {
          "number": 102
        },
        {
          "number": 103
        },
        {
          "availableColors": [
            {
              "name": "Clear",
              "default": true,
              "eventType": "controlchange",
              "value": 0,
              "string": "transparent",
              "fx": []
            },
            {
              "name": "Baby Blue (dim)",
              "eventType": "controlchange",
              "value": 1,
              "string": "#F3FAFE",
              "fx": []
            },
            {
              "name": "Baby Blue",
              "eventType": "controlchange",
              "value": 2,
              "string": "#ECF7FD",
              "fx": []
            },
            {
              "name": "Baby Blue (bright)",
              "eventType": "controlchange",
              "value": 3,
              "string": "#DFF9FF",
              "fx": []
            },
            {
              "name": "Pink",
              "eventType": "controlchange",
              "value": 4,
              "string": "#FF9FDA",
              "fx": []
            },
            {
              "name": "Red (dim)",
              "eventType": "controlchange",
              "value": 7,
              "string": "#F58A70",
              "fx": []
            },
            {
              "name": "Red",
              "eventType": "controlchange",
              "value": 6,
              "string": "#F36E56",
              "fx": []
            },
            {
              "name": "Red (bright)",
              "eventType": "controlchange",
              "value": 5,
              "string": "#F44336",
              "fx": []
            },
            {
              "name": "White",
              "eventType": "controlchange",
              "value": 8,
              "string": "white",
              "fx": []
            },
            {
              "name": "Off-White",
              "eventType": "controlchange",
              "value": 12,
              "string": "#F8F0E3",
              "fx": []
            },
            {
              "name": "Orange (dim)",
              "eventType": "controlchange",
              "value": 11,
              "string": "#FCBB6F",
              "fx": []
            },
            {
              "name": "Orange",
              "eventType": "controlchange",
              "value": 10,
              "string": "#FAAB4B",
              "fx": []
            },
            {
              "name": "Orange (bright)",
              "eventType": "controlchange",
              "value": 9,
              "string": "#FF9900",
              "fx": []
            },
            {
              "name": "Yellow-Green (dim)",
              "eventType": "controlchange",
              "value": 15,
              "string": "#EBEEA0",
              "fx": []
            },
            {
              "name": "Yellow-Green",
              "eventType": "controlchange",
              "value": 14,
              "string": "#E6EA89",
              "fx": []
            },
            {
              "name": "Yellow-Green (Bright)",
              "eventType": "controlchange",
              "value": 13,
              "string": "#E3FF6A",
              "fx": []
            },
            {
              "name": "SeaFoam-Green",
              "eventType": "controlchange",
              "value": 16,
              "string": "#93E9BE",
              "fx": []
            },
            {
              "name": "Light Green (dim)",
              "eventType": "controlchange",
              "value": 19,
              "string": "#bfdfb0",
              "fx": []
            },
            {
              "name": "Light Green",
              "eventType": "controlchange",
              "value": 18,
              "string": "#b0d89e",
              "fx": []
            },
            {
              "name": "Light Green (bright)",
              "eventType": "controlchange",
              "value": 17,
              "string": "#90ee90",
              "fx": []
            },
            {
              "name": "Blue-Green",
              "eventType": "controlchange",
              "value": 20,
              "string": "#7fffec",
              "fx": []
            },
            {
              "name": "Green (dim)",
              "eventType": "controlchange",
              "value": 23,
              "string": "#91C587",
              "fx": []
            },
            {
              "name": "Green",
              "eventType": "controlchange",
              "value": 22,
              "string": "#75BB6D",
              "fx": []
            },
            {
              "name": "Green (bright)",
              "eventType": "controlchange",
              "value": 21,
              "string": "#4CAF50",
              "fx": []
            },
            {
              "name": "Cyan (dim)",
              "eventType": "controlchange",
              "value": 31,
              "string": "#A5DDE7",
              "fx": []
            },
            {
              "name": "Cyan",
              "eventType": "controlchange",
              "value": 30,
              "string": "#8ED5E3",
              "fx": []
            },
            {
              "name": "Cyan (bright)",
              "eventType": "controlchange",
              "value": 29,
              "string": "#00FFFF",
              "fx": []
            },
            {
              "name": "Light Blue (dim)",
              "eventType": "controlchange",
              "value": 35,
              "string": "#A0DDF9",
              "fx": []
            },
            {
              "name": "Light Blue",
              "eventType": "controlchange",
              "value": 34,
              "string": "#86D5F7",
              "fx": []
            },
            {
              "name": "Light Blue (bright)",
              "eventType": "controlchange",
              "value": 33,
              "string": "#55D3FF",
              "fx": []
            },
            {
              "name": "Blue (dim)",
              "eventType": "controlchange",
              "value": 39,
              "string": "#A4CDED",
              "fx": []
            },
            {
              "name": "Blue",
              "eventType": "controlchange",
              "value": 38,
              "string": "#8DC3EA",
              "fx": []
            },
            {
              "name": "Blue (bright)",
              "eventType": "controlchange",
              "value": 37,
              "string": "#5FBCFF",
              "fx": []
            },
            {
              "name": "Deep Blue (dim)",
              "eventType": "controlchange",
              "value": 43,
              "string": "#A3B7DF",
              "fx": []
            },
            {
              "name": "Deep Blue",
              "eventType": "controlchange",
              "value": 44,
              "string": "#8FA9D8",
              "fx": []
            },
            {
              "name": "Deep Blue (bright)",
              "eventType": "controlchange",
              "value": 45,
              "string": "#6AA0FF",
              "fx": []
            },
            {
              "name": "Fuschia (dim)",
              "eventType": "controlchange",
              "value": 55,
              "string": "#d880b4",
              "fx": []
            },
            {
              "name": "Fuschia",
              "eventType": "controlchange",
              "value": 54,
              "string": "#d161a5",
              "fx": []
            },
            {
              "name": "Fuschia (bright)",
              "eventType": "controlchange",
              "value": 53,
              "string": "#ca2c92",
              "fx": []
            }
          ],
          "number": 104,
          "eventType": "controlchange"
        },
        {
          "number": 112
        },
        {
          "number": 113
        },
        {
          "number": 114
        },
        {
          "number": 115
        },
        {
          "number": 116
        },
        {
          "number": 117
        },
        {
          "number": 118
        },
        {
          "number": 119
        },
        {
          "availableColors": [
            {
              "name": "Clear",
              "default": true,
              "eventType": "controlchange",
              "value": 0,
              "string": "transparent",
              "fx": []
            },
            {
              "name": "Baby Blue (dim)",
              "eventType": "controlchange",
              "value": 1,
              "string": "#F3FAFE",
              "fx": []
            },
            {
              "name": "Baby Blue",
              "eventType": "controlchange",
              "value": 2,
              "string": "#ECF7FD",
              "fx": []
            },
            {
              "name": "Baby Blue (bright)",
              "eventType": "controlchange",
              "value": 3,
              "string": "#DFF9FF",
              "fx": []
            },
            {
              "name": "Pink",
              "eventType": "controlchange",
              "value": 4,
              "string": "#FF9FDA",
              "fx": []
            },
            {
              "name": "Red (dim)",
              "eventType": "controlchange",
              "value": 7,
              "string": "#F58A70",
              "fx": []
            },
            {
              "name": "Red",
              "eventType": "controlchange",
              "value": 6,
              "string": "#F36E56",
              "fx": []
            },
            {
              "name": "Red (bright)",
              "eventType": "controlchange",
              "value": 5,
              "string": "#F44336",
              "fx": []
            },
            {
              "name": "White",
              "eventType": "controlchange",
              "value": 8,
              "string": "white",
              "fx": []
            },
            {
              "name": "Off-White",
              "eventType": "controlchange",
              "value": 12,
              "string": "#F8F0E3",
              "fx": []
            },
            {
              "name": "Orange (dim)",
              "eventType": "controlchange",
              "value": 11,
              "string": "#FCBB6F",
              "fx": []
            },
            {
              "name": "Orange",
              "eventType": "controlchange",
              "value": 10,
              "string": "#FAAB4B",
              "fx": []
            },
            {
              "name": "Orange (bright)",
              "eventType": "controlchange",
              "value": 9,
              "string": "#FF9900",
              "fx": []
            },
            {
              "name": "Yellow-Green (dim)",
              "eventType": "controlchange",
              "value": 15,
              "string": "#EBEEA0",
              "fx": []
            },
            {
              "name": "Yellow-Green",
              "eventType": "controlchange",
              "value": 14,
              "string": "#E6EA89",
              "fx": []
            },
            {
              "name": "Yellow-Green (Bright)",
              "eventType": "controlchange",
              "value": 13,
              "string": "#E3FF6A",
              "fx": []
            },
            {
              "name": "SeaFoam-Green",
              "eventType": "controlchange",
              "value": 16,
              "string": "#93E9BE",
              "fx": []
            },
            {
              "name": "Light Green (dim)",
              "eventType": "controlchange",
              "value": 19,
              "string": "#bfdfb0",
              "fx": []
            },
            {
              "name": "Light Green",
              "eventType": "controlchange",
              "value": 18,
              "string": "#b0d89e",
              "fx": []
            },
            {
              "name": "Light Green (bright)",
              "eventType": "controlchange",
              "value": 17,
              "string": "#90ee90",
              "fx": []
            },
            {
              "name": "Blue-Green",
              "eventType": "controlchange",
              "value": 20,
              "string": "#7fffec",
              "fx": []
            },
            {
              "name": "Green (dim)",
              "eventType": "controlchange",
              "value": 23,
              "string": "#91C587",
              "fx": []
            },
            {
              "name": "Green",
              "eventType": "controlchange",
              "value": 22,
              "string": "#75BB6D",
              "fx": []
            },
            {
              "name": "Green (bright)",
              "eventType": "controlchange",
              "value": 21,
              "string": "#4CAF50",
              "fx": []
            },
            {
              "name": "Cyan (dim)",
              "eventType": "controlchange",
              "value": 31,
              "string": "#A5DDE7",
              "fx": []
            },
            {
              "name": "Cyan",
              "eventType": "controlchange",
              "value": 30,
              "string": "#8ED5E3",
              "fx": []
            },
            {
              "name": "Cyan (bright)",
              "eventType": "controlchange",
              "value": 29,
              "string": "#00FFFF",
              "fx": []
            },
            {
              "name": "Light Blue (dim)",
              "eventType": "controlchange",
              "value": 35,
              "string": "#A0DDF9",
              "fx": []
            },
            {
              "name": "Light Blue",
              "eventType": "controlchange",
              "value": 34,
              "string": "#86D5F7",
              "fx": []
            },
            {
              "name": "Light Blue (bright)",
              "eventType": "controlchange",
              "value": 33,
              "string": "#55D3FF",
              "fx": []
            },
            {
              "name": "Blue (dim)",
              "eventType": "controlchange",
              "value": 39,
              "string": "#A4CDED",
              "fx": []
            },
            {
              "name": "Blue",
              "eventType": "controlchange",
              "value": 38,
              "string": "#8DC3EA",
              "fx": []
            },
            {
              "name": "Blue (bright)",
              "eventType": "controlchange",
              "value": 37,
              "string": "#5FBCFF",
              "fx": []
            },
            {
              "name": "Deep Blue (dim)",
              "eventType": "controlchange",
              "value": 43,
              "string": "#A3B7DF",
              "fx": []
            },
            {
              "name": "Deep Blue",
              "eventType": "controlchange",
              "value": 44,
              "string": "#8FA9D8",
              "fx": []
            },
            {
              "name": "Deep Blue (bright)",
              "eventType": "controlchange",
              "value": 45,
              "string": "#6AA0FF",
              "fx": []
            },
            {
              "name": "Fuschia (dim)",
              "eventType": "controlchange",
              "value": 55,
              "string": "#d880b4",
              "fx": []
            },
            {
              "name": "Fuschia",
              "eventType": "controlchange",
              "value": 54,
              "string": "#d161a5",
              "fx": []
            },
            {
              "name": "Fuschia (bright)",
              "eventType": "controlchange",
              "value": 53,
              "string": "#ca2c92",
              "fx": []
            }
          ],
          "number": 105,
          "eventType": "controlchange"
        }
      ],
      "inputDefaults": {
        "availableColors": [
          {
            "default": true,
            "eventType": "noteon",
            "fx": [],
            "name": "Clear",
            "string": "transparent",
            "value": 0
          },
          {
            "eventType": "noteon",
            "fx": [],
            "name": "Baby Blue (dim)",
            "string": "#F3FAFE",
            "value": 1
          },
          {
            "eventType": "noteon",
            "fx": [],
            "name": "Baby Blue",
            "string": "#ECF7FD",
            "value": 2
          },
          {
            "eventType": "noteon",
            "fx": [],
            "name": "Baby Blue (bright)",
            "string": "#DFF9FF",
            "value": 3
          },
          {
            "eventType": "noteon",
            "fx": [],
            "name": "Pink",
            "string": "#FF9FDA",
            "value": 4
          },
          {
            "eventType": "noteon",
            "fx": [],
            "name": "Red (dim)",
            "string": "#F58A70",
            "value": 7
          },
          {
            "eventType": "noteon",
            "fx": [],
            "name": "Red",
            "string": "#F36E56",
            "value": 6
          },
          {
            "eventType": "noteon",
            "fx": [],
            "name": "Red (bright)",
            "string": "#F44336",
            "value": 5
          },
          {
            "eventType": "noteon",
            "fx": [],
            "name": "White",
            "string": "white",
            "value": 8
          },
          {
            "eventType": "noteon",
            "fx": [],
            "name": "Off-White",
            "string": "#F8F0E3",
            "value": 12
          },
          {
            "eventType": "noteon",
            "fx": [],
            "name": "Orange (dim)",
            "string": "#FCBB6F",
            "value": 11
          },
          {
            "eventType": "noteon",
            "fx": [],
            "name": "Orange",
            "string": "#FAAB4B",
            "value": 10
          },
          {
            "eventType": "noteon",
            "fx": [],
            "name": "Orange (bright)",
            "string": "#FF9900",
            "value": 9
          },
          {
            "eventType": "noteon",
            "fx": [],
            "name": "Yellow-Green (dim)",
            "string": "#EBEEA0",
            "value": 15
          },
          {
            "eventType": "noteon",
            "fx": [],
            "name": "Yellow-Green",
            "string": "#E6EA89",
            "value": 14
          },
          {
            "eventType": "noteon",
            "fx": [],
            "name": "Yellow-Green (Bright)",
            "string": "#E3FF6A",
            "value": 13
          },
          {
            "eventType": "noteon",
            "fx": [],
            "name": "SeaFoam-Green",
            "string": "#93E9BE",
            "value": 16
          },
          {
            "eventType": "noteon",
            "fx": [],
            "name": "Light Green (dim)",
            "string": "#bfdfb0",
            "value": 19
          },
          {
            "eventType": "noteon",
            "fx": [],
            "name": "Light Green",
            "string": "#b0d89e",
            "value": 18
          },
          {
            "eventType": "noteon",
            "fx": [],
            "name": "Light Green (bright)",
            "string": "#90ee90",
            "value": 17
          },
          {
            "eventType": "noteon",
            "fx": [],
            "name": "Blue-Green",
            "string": "#7fffec",
            "value": 20
          },
          {
            "eventType": "noteon",
            "fx": [],
            "name": "Green (dim)",
            "string": "#91C587",
            "value": 23
          },
          {
            "eventType": "noteon",
            "fx": [],
            "name": "Green",
            "string": "#75BB6D",
            "value": 22
          },
          {
            "eventType": "noteon",
            "fx": [],
            "name": "Green (bright)",
            "string": "#4CAF50",
            "value": 21
          },
          {
            "eventType": "noteon",
            "fx": [],
            "name": "Cyan (dim)",
            "string": "#A5DDE7",
            "value": 31
          },
          {
            "eventType": "noteon",
            "fx": [],
            "name": "Cyan",
            "string": "#8ED5E3",
            "value": 30
          },
          {
            "eventType": "noteon",
            "fx": [],
            "name": "Cyan (bright)",
            "string": "#00FFFF",
            "value": 29
          },
          {
            "eventType": "noteon",
            "fx": [],
            "name": "Light Blue (dim)",
            "string": "#A0DDF9",
            "value": 35
          },
          {
            "eventType": "noteon",
            "fx": [],
            "name": "Light Blue",
            "string": "#86D5F7",
            "value": 34
          },
          {
            "eventType": "noteon",
            "fx": [],
            "name": "Light Blue (bright)",
            "string": "#55D3FF",
            "value": 33
          },
          {
            "eventType": "noteon",
            "fx": [],
            "name": "Blue (dim)",
            "string": "#A4CDED",
            "value": 39
          },
          {
            "eventType": "noteon",
            "fx": [],
            "name": "Blue",
            "string": "#8DC3EA",
            "value": 38
          },
          {
            "eventType": "noteon",
            "fx": [],
            "name": "Blue (bright)",
            "string": "#5FBCFF",
            "value": 37
          },
          {
            "eventType": "noteon",
            "fx": [],
            "name": "Deep Blue (dim)",
            "string": "#A3B7DF",
            "value": 43
          },
          {
            "eventType": "noteon",
            "fx": [],
            "name": "Deep Blue",
            "string": "#8FA9D8",
            "value": 44
          },
          {
            "eventType": "noteon",
            "fx": [],
            "name": "Deep Blue (bright)",
            "string": "#6AA0FF",
            "value": 45
          },
          {
            "eventType": "noteon",
            "fx": [],
            "name": "Fuschia (dim)",
            "string": "#d880b4",
            "value": 55
          },
          {
            "eventType": "noteon",
            "fx": [],
            "name": "Fuschia",
            "string": "#d161a5",
            "value": 54
          },
          {
            "eventType": "noteon",
            "fx": [],
            "name": "Fuschia (bright)",
            "string": "#ca2c92",
            "value": 53
          }
        ],
        "type": "pad",
        "width": 0.7,
        "height": 0.7,
        "shape": "rect",
        "overrideable": true,
        "response": "gate",
        "eventType": "noteon/noteoff",
        "channel": 0
      }
    },
    {
      "id": "Knobs",
      "nRows": 1,
      "nCols": 8,
      "width": 6.375,
      "height": 0.375,
      "left": 3.25,
      "bottom": 6,
      "inputs": [
        {
          "number": 21
        },
        {
          "number": 22
        },
        {
          "number": 23
        },
        {
          "number": 24
        },
        {
          "number": 25
        },
        {
          "number": 26
        },
        {
          "number": 27
        },
        {
          "number": 28
        }
      ],
      "inputDefaults": {
        "availableColors": [],
        "type": "knob",
        "width": 0.375,
        "height": 0.375,
        "shape": "circle",
        "overrideable": true,
        "response": "continuous",
        "eventType": "controlchange",
        "channel": 15
      }
    },
    {
      "id": "Transport",
      "nRows": 1,
      "nCols": 2,
      "width": 1.25,
      "height": 0.25,
      "left": 11.125,
      "bottom": 3.75,
      "inputs": [
        {
          "number": 115
        },
        {
          "number": 117
        }
      ],
      "inputDefaults": {
        "availableColors": [
          {
            "default": true,
            "eventType": "controlchange",
            "fx": [],
            "name": "Clear",
            "string": "transparent",
            "value": 0
          },
          {
            "eventType": "controlchange",
            "fx": [],
            "name": "White (dim)",
            "string": "rgba(255,255,255,0.5)",
            "value": 1
          },
          {
            "eventType": "controlchange",
            "fx": [],
            "name": "White",
            "string": "white",
            "value": 127
          }
        ],
        "type": "pad",
        "width": 0.5,
        "height": 0.25,
        "shape": "rect",
        "overrideable": true,
        "response": "gate",
        "eventType": "controlchange",
        "channel": 15
      }
    },
    {
      "id": "Track",
      "nRows": 1,
      "nCols": 2,
      "width": 1.25,
      "height": 0.25,
      "left": 11.125,
      "bottom": 4.625,
      "inputs": [
        {
          "number": 115
        },
        {
          "number": 117
        }
      ],
      "inputDefaults": {
        "availableColors": [],
        "type": "pad",
        "width": 0.5,
        "height": 0.25,
        "shape": "rect",
        "overrideable": false,
        "response": "gate",
        "eventType": "controlchange",
        "channel": 15
      }
    }
  ]
}